onedrive_pdf_downloader/__init__.py
onedrive_pdf_downloader/__main__.py
onedrive_pdf_downloader/cli.py
onedrive_pdf_downloader/logging_config.py
onedrive_pdf_downloader/browser/__init__.py
onedrive_pdf_downloader/browser/constants.py
onedrive_pdf_downloader/browser/factory.py
onedrive_pdf_downloader/browser/utils.py
onedrive_pdf_downloader/cache/__init__.py
onedrive_pdf_downloader/cache/finder.py
onedrive_pdf_downloader/core/__init__.py
onedrive_pdf_downloader/core/export.py
onedrive_pdf_downloader/core/workflow.py
onedrive_pdf_downloader/utils/__init__.py
onedrive_pdf_downloader/utils/file_utils.py
onedrive_pdf_downloader-1.3.0.dist-info/METADATA
onedrive_pdf_downloader-1.3.0.dist-info/WHEEL
onedrive_pdf_downloader-1.3.0.dist-info/entry_points.txt
onedrive_pdf_downloader-1.3.0.dist-info/licenses/LICENSE
onedrive_pdf_downloader-1.3.0.dist-info/RECORD
