Metadata-Version: 2.4
Name: onedrive_pdf_downloader
Version: 1.3.0
Summary: A tool to download private PDF files from OneDrive using Selenium.
Project-URL: Repository, https://github.com/Flying-Bunny-Devs/Onedrive-Private-PDF-Downloader
Project-URL: Homepage, https://github.com/Flying-Bunny-Devs/Onedrive-Private-PDF-Downloader
Project-URL: Documentation, https://github.com/Flying-Bunny-Devs/Onedrive-Private-PDF-Downloader/blob/master/README.md
Project-URL: Issues, https://github.com/Flying-Bunny-Devs/Onedrive-Private-PDF-Downloader/issues
Project-URL: Changelog, https://github.com/Flying-Bunny-Devs/Onedrive-Private-PDF-Downloader/blob/master/CHANGELOG.md
Author-email: Francesco146 <49027005+Francesco146@users.noreply.github.com>, willnaoosmith <55159911+willnaoosmith@users.noreply.github.com>
Maintainer-email: Francesco146 <49027005+Francesco146@users.noreply.github.com>, willnaoosmith <55159911+willnaoosmith@users.noreply.github.com>
License: MIT License
License-File: LICENSE
Keywords: downloader,onedrive,pdf,selenium
Classifier: Development Status :: 5 - Production/Stable
Classifier: Environment :: Console
Classifier: Intended Audience :: Developers
Classifier: License :: OSI Approved :: MIT License
Classifier: Operating System :: OS Independent
Classifier: Programming Language :: Python
Classifier: Programming Language :: Python :: 3 :: Only
Classifier: Programming Language :: Python :: 3.10
Classifier: Programming Language :: Python :: 3.11
Classifier: Programming Language :: Python :: 3.12
Classifier: Programming Language :: Python :: 3.13
Classifier: Topic :: Utilities
Requires-Python: >=3.10
Requires-Dist: argparse==1.4.0
Requires-Dist: attrs==25.3.0
Requires-Dist: certifi==2025.4.26
Requires-Dist: deprecated==1.2.18
Requires-Dist: h11==0.16.0
Requires-Dist: idna==3.10
Requires-Dist: img2pdf==0.6.1
Requires-Dist: lxml==5.4.0
Requires-Dist: outcome==1.3.0.post0
Requires-Dist: packaging==25.0
Requires-Dist: pikepdf==9.7.0
Requires-Dist: pillow==11.2.1
Requires-Dist: pysocks==1.7.1
Requires-Dist: selenium==4.31.0
Requires-Dist: sniffio==1.3.1
Requires-Dist: sortedcontainers==2.4.0
Requires-Dist: trio-websocket==0.12.2
Requires-Dist: trio==0.30.0
Requires-Dist: typing-extensions==4.13.2
Requires-Dist: urllib3==2.4.0
Requires-Dist: websocket-client==1.8.0
Requires-Dist: wrapt==1.17.2
Requires-Dist: wsproto==1.2.0
